llama_index/packs/finchat/BUILD
llama_index/packs/finchat/__init__.py
llama_index/packs/finchat/base.py
llama_index_packs_finchat-0.3.0.dist-info/METADATA
llama_index_packs_finchat-0.3.0.dist-info/WHEEL
llama_index_packs_finchat-0.3.0.dist-info/RECORD
