Metadata-Version: 2.1
Name: llama-index-packs-finchat
Version: 0.3.0
Summary: llama-index packs implementation of a hierarchical agent for finance chat.
License: MIT
Keywords: agent,finance,finchat
Author: Ishan Gupta
Author-email: 345ishaan@gmail.com
Maintainer: 345ishaan
Requires-Python: >=3.9,<3.12
Classifier: License :: OSI Approved :: MIT License
Classifier: Programming Language :: Python :: 3
Classifier: Programming Language :: Python :: 3.9
Classifier: Programming Language :: Python :: 3.10
Classifier: Programming Language :: Python :: 3.11
Requires-Dist: llama-index-agent-openai (>=0.4.0,<0.5.0)
Requires-Dist: llama-index-core (>=0.12.0,<0.13.0)
Requires-Dist: llama-index-tools-finance (>=0.3.0,<0.4.0)
Requires-Dist: tavily-python (>=0.3.1,<0.4.0)
